hw2/latex_generator/__init__.py
hw2/latex_generator/latex_generator.py
latex_generator_neki419-0.1.0.dist-info/METADATA
latex_generator_neki419-0.1.0.dist-info/WHEEL
latex_generator_neki419-0.1.0.dist-info/RECORD
