Metadata-Version: 2.3
Name: latex-generator-neki419
Version: 0.1.0
Summary: Library for generating LaTeX tables and images
License: MIT
Author: Седляр Никита
Author-email: nasedliar@edu.hse.ru
Requires-Python: >=3.12
Classifier: License :: OSI Approved :: MIT License
Classifier: Programming Language :: Python :: 3
Classifier: Programming Language :: Python :: 3.12
Classifier: Programming Language :: Python :: 3.13
